baryon_cycle/__init__.py
baryon_cycle-0.0.1.dist-info/licenses/LICENSE
baryon_cycle-0.0.1.dist-info/METADATA
baryon_cycle-0.0.1.dist-info/WHEEL
baryon_cycle-0.0.1.dist-info/top_level.txt
baryon_cycle-0.0.1.dist-info/RECORD
