Metadata-Version: 2.4
Name: baryon-cycle
Version: 0.0.1
Summary: BAGS: Revealing baryon cycle around galaxies with stacking analysis
Author-email: Yangyao Chen <yangyaochen.astro@foxmail.com>, Chengyu Ma <3065616846@qq.com>, Enci Wang <ecwang16@ustc.edu.cn>
Project-URL: Repository, https://github.com/ChenYangyao/baryon-cycle.git
Classifier: Programming Language :: Python :: 3
Classifier: License :: OSI Approved :: MIT License
Classifier: Operating System :: OS Independent
Requires-Python: >=3.12
License-File: LICENSE
Requires-Dist: pyhipp>=0.3.6
Requires-Dist: flake8
Requires-Dist: pytest>=7.0.0
Dynamic: license-file
